pyrdb/__init__.py
pyrdb/crm.py
pyrdb/emp.py
pyrdb/gov.py
pyrdb/hr.py
pyrdb/srm.py
pyrdb/wulai.py
pyrdb-1.1.5.dist-info/LICENSE
pyrdb-1.1.5.dist-info/METADATA
pyrdb-1.1.5.dist-info/WHEEL
pyrdb-1.1.5.dist-info/top_level.txt
pyrdb-1.1.5.dist-info/RECORD
