Metadata-Version: 2.1
Name: pyrdb
Version: 1.1.5
Summary: reshape data base in py language 
Home-page: http://www.reshapedata.com
Author: Reshapedata
Author-email: hulilei@takewiki.com.cn
License: Apache License
Keywords: reshapedata,rdb,pyrdb
Platform: UNKNOWN
Requires-Python: >=3.6
Requires-Dist: pymssql
